infer/lib/audio.py
infer/lib/infer_pack/attentions.py
infer/lib/infer_pack/commons.py
infer/lib/infer_pack/models.py
infer/lib/infer_pack/models_onnx.py
infer/lib/infer_pack/modules/F0Predictor/DioF0Predictor.py
infer/lib/infer_pack/modules/F0Predictor/F0Predictor.py
infer/lib/infer_pack/modules/F0Predictor/HarvestF0Predictor.py
infer/lib/infer_pack/modules/F0Predictor/PMF0Predictor.py
infer/lib/infer_pack/modules/F0Predictor/__init__.py
infer/lib/infer_pack/modules.py
infer/lib/infer_pack/onnx_inference.py
infer/lib/infer_pack/transforms.py
infer/lib/rmvpe.py
infer/lib/slicer2.py
infer/lib/train/data_utils.py
infer/lib/train/losses.py
infer/lib/train/mel_processing.py
infer/lib/train/process_ckpt.py
infer/lib/train/utils.py
infer/lib/uvr5_pack/lib_v5/dataset.py
infer/lib/uvr5_pack/lib_v5/layers.py
infer/lib/uvr5_pack/lib_v5/layers_123812KB .py
infer/lib/uvr5_pack/lib_v5/layers_123821KB.py
infer/lib/uvr5_pack/lib_v5/layers_33966KB.py
infer/lib/uvr5_pack/lib_v5/layers_537227KB.py
infer/lib/uvr5_pack/lib_v5/layers_537238KB.py
infer/lib/uvr5_pack/lib_v5/layers_new.py
infer/lib/uvr5_pack/lib_v5/model_param_init.py
infer/lib/uvr5_pack/lib_v5/modelparams/1band_sr16000_hl512.json
infer/lib/uvr5_pack/lib_v5/modelparams/1band_sr32000_hl512.json
infer/lib/uvr5_pack/lib_v5/modelparams/1band_sr33075_hl384.json
infer/lib/uvr5_pack/lib_v5/modelparams/1band_sr44100_hl1024.json
infer/lib/uvr5_pack/lib_v5/modelparams/1band_sr44100_hl256.json
infer/lib/uvr5_pack/lib_v5/modelparams/1band_sr44100_hl512.json
infer/lib/uvr5_pack/lib_v5/modelparams/1band_sr44100_hl512_cut.json
infer/lib/uvr5_pack/lib_v5/modelparams/2band_32000.json
infer/lib/uvr5_pack/lib_v5/modelparams/2band_44100_lofi.json
infer/lib/uvr5_pack/lib_v5/modelparams/2band_48000.json
infer/lib/uvr5_pack/lib_v5/modelparams/3band_44100.json
infer/lib/uvr5_pack/lib_v5/modelparams/3band_44100_mid.json
infer/lib/uvr5_pack/lib_v5/modelparams/3band_44100_msb2.json
infer/lib/uvr5_pack/lib_v5/modelparams/4band_44100.json
dls_rvc-0.1.2.dist-info/LICENSE
dls_rvc-0.1.2.dist-info/METADATA
dls_rvc-0.1.2.dist-info/WHEEL
dls_rvc-0.1.2.dist-info/RECORD
