Metadata-Version: 2.1
Name: dls_rvc
Version: 0.1.2
Summary: 
License: MIT
Author: lj1995
Requires-Python: >=3.8,<4.0
Classifier: License :: OSI Approved :: MIT License
Classifier: Programming Language :: Python :: 3
Classifier: Programming Language :: Python :: 3.8
Classifier: Programming Language :: Python :: 3.9
Classifier: Programming Language :: Python :: 3.10
Classifier: Programming Language :: Python :: 3.11
Requires-Dist: Cython (>=0.29.34,<0.30.0)
Requires-Dist: Jinja2 (>=3.1.2,<4.0.0)
Requires-Dist: Markdown (>=3.4.3,<4.0.0)
Requires-Dist: Pillow (==9.3.0)
Requires-Dist: PyYAML (>=6.0,<7.0)
Requires-Dist: Werkzeug (>=2.2.3,<3.0.0)
Requires-Dist: absl-py (>=1.4.0,<2.0.0)
Requires-Dist: audioread (>=3.0.0,<4.0.0)
Requires-Dist: colorama (>=0.4.6,<0.5.0)
Requires-Dist: fairseq (>=0.12.2,<0.13.0)
Requires-Dist: faiss-cpu (>=1.7.2,<2.0.0)
Requires-Dist: ffmpeg-python (>=0.2.0,<0.3.0)
Requires-Dist: fsspec (>=2023.3.0,<2024.0.0)
Requires-Dist: functorch (>=2.0.0,<3.0.0)
Requires-Dist: future (>=0.18.3,<0.19.0)
Requires-Dist: gradio (>=3.34.0,<4.0.0)
Requires-Dist: json5 (>=0.9.11,<0.10.0)
Requires-Dist: librosa (==0.9.1)
Requires-Dist: llvmlite (==0.39.0)
Requires-Dist: matplotlib (>=3.7.1,<4.0.0)
Requires-Dist: matplotlib-inline (>=0.1.6,<0.2.0)
Requires-Dist: numba (==0.56.4)
Requires-Dist: numpy (==1.23.5)
Requires-Dist: praat-parselmouth (>=0.4.3,<0.5.0)
Requires-Dist: pyasn1 (>=0.4.8,<0.5.0)
Requires-Dist: pyasn1-modules (>=0.2.8,<0.3.0)
Requires-Dist: pydub (>=0.25.1,<0.26.0)
Requires-Dist: python-dotenv (>=1.0.0,<2.0.0)
Requires-Dist: pyworld (>=0.3.2,<0.4.0)
Requires-Dist: resampy (>=0.4.2,<0.5.0)
Requires-Dist: scikit-learn (>=1.2.2,<2.0.0)
Requires-Dist: scipy (>=1.10.0)
Requires-Dist: soundfile (>=0.12.1,<0.13.0)
Requires-Dist: starlette (>=0.27.0,<0.28.0)
Requires-Dist: sympy (>=1.11.1,<2.0.0)
Requires-Dist: tabulate (>=0.9.0,<0.10.0)
Requires-Dist: tensorboard (>=2.12.1,<3.0.0)
Requires-Dist: tensorboard-data-server (>=0.7.0,<0.8.0)
Requires-Dist: tensorboard-plugin-wit (>=1.8.1,<2.0.0)
Requires-Dist: tensorboardX (>=2.6,<3.0)
Requires-Dist: torch (>=2.0.0,<3.0.0)
Requires-Dist: torchaudio (>=2.0.1,<3.0.0)
Requires-Dist: torchcrepe (==0.0.20)
Requires-Dist: torchgen (>=0.0.1,<0.0.2)
Requires-Dist: tornado (>=6.3,<7.0)
Requires-Dist: tqdm (>=4.65.0,<5.0.0)
Requires-Dist: uc-micro-py (>=1.0.1,<2.0.0)
Requires-Dist: uvicorn (>=0.21.1,<0.22.0)
